README.md
setup.py
nexus/__init__.py
nexus/client.py
nexus/server.py
nexus/platform/__init__.py
nexus/platform/thrift.py
nexus_rpc.egg-info/PKG-INFO
nexus_rpc.egg-info/SOURCES.txt
nexus_rpc.egg-info/dependency_links.txt
nexus_rpc.egg-info/requires.txt
nexus_rpc.egg-info/top_level.txt