Metadata-Version: 1.1
Name: nexus-rpc
Version: 0.1.0
Summary: Nexus is a http-based rpc framework.
Home-page: https://github.com/JZQT/nexus-rpc
Author: JZQT
Author-email: 561484726@qq.com
License: MIT
Platform: UNKNOWN
Classifier: Programming Language :: Python :: 3
Classifier: Programming Language :: Python :: 3.5
Classifier: Programming Language :: Python :: 3.6
Classifier: Programming Language :: Python :: Implementation :: CPython
Classifier: Programming Language :: Python :: Implementation :: PyPy
